truelle/__init__.py
truelle-0.0.1.dist-info/LICENSE
truelle-0.0.1.dist-info/WHEEL
truelle-0.0.1.dist-info/METADATA
truelle-0.0.1.dist-info/RECORD
