Metadata-Version: 2.1
Name: truelle
Version: 0.0.1
Summary: A tiny web scraping library
License: MIT
Author: Jonathan Geslin
Author-email: jonathan.geslin@gmail.com
Requires-Python: >=3.9,<4.0
Classifier: License :: OSI Approved :: MIT License
Classifier: Programming Language :: Python :: 3
Classifier: Programming Language :: Python :: 3.10
Classifier: Programming Language :: Python :: 3.9
Requires-Dist: parsel (>=1.6.0,<2.0.0)
Requires-Dist: requests (>=2.28.1,<3.0.0)
